LICENSE
MANIFEST.in
README.md
pyproject.toml
setup.py
ethrpc_accounts/__init__.py
ethrpc_accounts/account.py
ethrpc_accounts/datastructures.py
ethrpc_accounts/messages.py
ethrpc_accounts/py.typed
ethrpc_accounts.egg-info/PKG-INFO
ethrpc_accounts.egg-info/SOURCES.txt
ethrpc_accounts.egg-info/dependency_links.txt
ethrpc_accounts.egg-info/not-zip-safe
ethrpc_accounts.egg-info/requires.txt
ethrpc_accounts.egg-info/top_level.txt
ethrpc_accounts/_utils/__init__.py
ethrpc_accounts/_utils/legacy_transactions.py
ethrpc_accounts/_utils/signing.py
ethrpc_accounts/_utils/transaction_utils.py
ethrpc_accounts/_utils/typed_transactions.py
ethrpc_accounts/_utils/validation.py
ethrpc_accounts/_utils/structured_data/__init__.py
ethrpc_accounts/_utils/structured_data/hashing.py
ethrpc_accounts/_utils/structured_data/validation.py
ethrpc_accounts/hdaccount/__init__.py
ethrpc_accounts/hdaccount/_utils.py
ethrpc_accounts/hdaccount/deterministic.py
ethrpc_accounts/hdaccount/mnemonic.py
ethrpc_accounts/hdaccount/wordlist/chinese_simplified.txt
ethrpc_accounts/hdaccount/wordlist/chinese_traditional.txt
ethrpc_accounts/hdaccount/wordlist/czech.txt
ethrpc_accounts/hdaccount/wordlist/english.txt
ethrpc_accounts/hdaccount/wordlist/french.txt
ethrpc_accounts/hdaccount/wordlist/italian.txt
ethrpc_accounts/hdaccount/wordlist/japanese.txt
ethrpc_accounts/hdaccount/wordlist/korean.txt
ethrpc_accounts/hdaccount/wordlist/spanish.txt
ethrpc_accounts/signers/__init__.py
ethrpc_accounts/signers/base.py
ethrpc_accounts/signers/local.py
myenv/lib/python3.10/site-packages/Crypto/__init__.pyi
myenv/lib/python3.10/site-packages/Crypto/Cipher/AES.pyi
myenv/lib/python3.10/site-packages/Crypto/Cipher/ARC2.pyi
myenv/lib/python3.10/site-packages/Crypto/Cipher/ARC4.pyi
myenv/lib/python3.10/site-packages/Crypto/Cipher/Blowfish.pyi
myenv/lib/python3.10/site-packages/Crypto/Cipher/CAST.pyi
myenv/lib/python3.10/site-packages/Crypto/Cipher/ChaCha20.pyi
myenv/lib/python3.10/site-packages/Crypto/Cipher/ChaCha20_Poly1305.pyi
myenv/lib/python3.10/site-packages/Crypto/Cipher/DES.pyi
myenv/lib/python3.10/site-packages/Crypto/Cipher/DES3.pyi
myenv/lib/python3.10/site-packages/Crypto/Cipher/PKCS1_OAEP.pyi
