Metadata-Version: 2.1
Name: ethrpc-accounts
Version: 0.9.2
Summary: ethrpc-accounts: Sign Ethereum transactions and messages with local private keys
Home-page: https://github.com/ethereum/ethrpc-accounts
Author: The Ethereum Foundation
Author-email: snakecharmers@ethereum.org
License: MIT
Keywords: ethereum
Platform: UNKNOWN
Classifier: Development Status :: 3 - Alpha
Classifier: Intended Audience :: Developers
Classifier: License :: OSI Approved :: MIT License
Classifier: Natural Language :: English
Classifier: Programming Language :: Python :: 3
Classifier: Programming Language :: Python :: 3.7
Classifier: Programming Language :: Python :: 3.8
Classifier: Programming Language :: Python :: 3.9
Classifier: Programming Language :: Python :: 3.10
Classifier: Programming Language :: Python :: 3.11
Requires-Python: >=3.7, <4
Provides-Extra: test
Provides-Extra: lint
Provides-Extra: doc
Provides-Extra: dev
License-File: LICENSE
